README.md
setup.py
gpr4im/__init__.py
gpr4im/cov_tools.py
gpr4im/fg_tools.py
gpr4im/obs_tools.py
gpr4im/pk_tools.py
gpr4im.egg-info/PKG-INFO
gpr4im.egg-info/SOURCES.txt
gpr4im.egg-info/dependency_links.txt
gpr4im.egg-info/requires.txt
gpr4im.egg-info/top_level.txt