Metadata-Version: 2.1
Name: gpr4im
Version: 1.0.1
Summary: Python package for using GPR as a foreground removal technique in 21cm intensity mapping
Home-page: https://github.com/paulassoares/gpr4im
Author: Paula S. Soares
Author-email: p.s.soares@qmul.ac.uk
License: UNKNOWN
Platform: UNKNOWN
